uvicorn3/__init__.py
uvicorn3/__main__.py
uvicorn3/_subprocess.py
uvicorn3/_types.py
uvicorn3/config.py
uvicorn3/importer.py
uvicorn3/lifespan/__init__.py
uvicorn3/lifespan/off.py
uvicorn3/lifespan/on.py
uvicorn3/logging.py
uvicorn3/loops/__init__.py
uvicorn3/loops/asyncio.py
uvicorn3/loops/auto.py
uvicorn3/loops/uvloop.py
uvicorn3/main.py
uvicorn3/middleware/__init__.py
uvicorn3/middleware/asgi2.py
uvicorn3/middleware/message_logger.py
uvicorn3/middleware/proxy_headers.py
uvicorn3/middleware/wsgi.py
uvicorn3/protocols/__init__.py
uvicorn3/protocols/http/__init__.py
uvicorn3/protocols/http/auto.py
uvicorn3/protocols/http/flow_control.py
uvicorn3/protocols/http/h11_impl.py
uvicorn3/protocols/http/httptools_impl.py
uvicorn3/protocols/utils.py
uvicorn3/protocols/websockets/__init__.py
uvicorn3/protocols/websockets/auto.py
uvicorn3/protocols/websockets/websockets_impl.py
uvicorn3/protocols/websockets/wsproto_impl.py
uvicorn3/server.py
uvicorn3/supervisors/__init__.py
uvicorn3/supervisors/basereload.py
uvicorn3/supervisors/multiprocess.py
uvicorn3/supervisors/statreload.py
uvicorn3/supervisors/watchfilesreload.py
uvicorn3/workers.py
uvicorn3-0.1.2.dist-info/entry_points.txt
uvicorn3-0.1.2.dist-info/LICENSE
uvicorn3-0.1.2.dist-info/METADATA
uvicorn3-0.1.2.dist-info/WHEEL
uvicorn3-0.1.2.dist-info/RECORD
